{
  "podcasts": [
    {
      "id": 1,
      "title": "Show da Fé",
      "artist": "RR Soares",
      "cover": "https://www.bestrongest.com.br/podcasts/showdafe/showdafe-album-cover.png",
      "tracks": [
        {
          "id": "5150",
          "title": "Venha a mim e beba",
          "artist": "RR Soares",
          "url": "https://www.bestrongest.com.br/podcasts/showdafe/files/5150.mp3",
          "artwork": "https://www.bestrongest.com.br/podcasts/showdafe/showdafe-album-cover.png"
        },
        {
          "id": "5149",
          "title": "Tome posse da sua terra",
          "artist": "RR Soares",
          "url": "https://www.bestrongest.com.br/podcasts/showdafe/files/5149.mp3",
          "artwork": "https://www.bestrongest.com.br/podcasts/showdafe/showdafe-album-cover.png"
        },
        {
          "id": "5148",
          "title": "Busque a Deus",
          "artist": "RR Soares",
          "url": "https://www.bestrongest.com.br/podcasts/showdafe/files/5148.mp3",
          "artwork": "https://www.bestrongest.com.br/podcasts/showdafe/showdafe-album-cover.png"
        },       
        {
          "id": "5147",
          "title": "Em Cristo somos inocentados",
          "artist": "RR Soares",
          "url": "https://www.bestrongest.com.br/podcasts/showdafe/files/5147.mp3",
          "artwork": "https://www.bestrongest.com.br/podcasts/showdafe/showdafe-album-cover.png"
        },        
         {
          "id": "5146",
          "title": "A terra da Promessa",
          "artist": "RR Soares",
          "url": "https://www.bestrongest.com.br/podcasts/showdafe/files/5146.mp3",
          "artwork": "https://www.bestrongest.com.br/podcasts/showdafe/showdafe-album-cover.png"
        },
         {
          "id": "5145",
          "title": "Justificados por Jesus",
          "artist": "RR Soares",
          "url": "https://www.bestrongest.com.br/podcasts/showdafe/files/5145.mp3",
          "artwork": "https://www.bestrongest.com.br/podcasts/showdafe/showdafe-album-cover.png"
        },
        {
          "id": "5144",
          "title": "O Evangelho justifica o homem",
          "artist": "RR Soares",
          "url": "https://www.bestrongest.com.br/podcasts/showdafe/files/5144.mp3",
          "artwork": "https://www.bestrongest.com.br/podcasts/showdafe/showdafe-album-cover.png"
        },
        {
          "id": "5143",
          "title": "Acredite no Senhor",
          "artist": "RR Soares",
          "url": "https://www.bestrongest.com.br/podcasts/showdafe/files/5143.mp3",
          "artwork": "https://www.bestrongest.com.br/podcasts/showdafe/showdafe-album-cover.png"
        },
        {
          "id": "5142",
          "title": "O privilégio de servir a Deus",
          "artist": "RR Soares",
          "url": "https://www.bestrongest.com.br/podcasts/showdafe/files/5142.mp3",
          "artwork": "https://www.bestrongest.com.br/podcasts/showdafe/showdafe-album-cover.png"
        },
        {
          "id": "5141",
          "title": "Os dons de Deus",
          "artist": "RR Soares",
          "url": "https://www.bestrongest.com.br/podcasts/showdafe/files/5141.mp3",
          "artwork": "https://www.bestrongest.com.br/podcasts/showdafe/showdafe-album-cover.png"
        }
      ]
    },
    {
      "id": 2,
      "title": "Curso Fé",
      "artist": "RR Soares",
      "cover": "https://www.bestrongest.com.br/podcasts/cursofe/cursofe-album-cover.png",
      "tracks": [
        {
          "id": "1",
          "title": "Determinação",
          "artist": "RR Soares",
          "url": "https://www.bestrongest.com.br/podcasts/cursofe/files/cursofe01.mp3",
          "artwork": "https://www.bestrongest.com.br/podcasts/cursofe/cursofe-album-cover.png"
        },
        {
          "id": "2",
          "title": "Os cinco passos da vitoria",
          "artist": "RR Soares",
          "url": "https://www.bestrongest.com.br/podcasts/cursofe/files/cursofe02.mp3",
          "artwork": "https://www.bestrongest.com.br/podcasts/cursofe/cursofe-album-cover.png"
        },
        {
          "id": "3",
          "title": "Os nossos direitos as bênçãos",
          "artist": "RR Soares",
          "url": "https://www.bestrongest.com.br/podcasts/cursofe/files/cursofe03.mp3",
          "artwork": "https://www.bestrongest.com.br/podcasts/cursofe/cursofe-album-cover.png"
        },
        {
          "id": "4",
          "title": "O nome de Jesus",
          "artist": "RR Soares",
          "url": "https://www.bestrongest.com.br/podcasts/cursofe/files/cursofe04.mp3",
          "artwork": "https://www.bestrongest.com.br/podcasts/cursofe/cursofe-album-cover.png"
        },
        {
          "id": "5",
          "title": "A fórmula da oração",
          "artist": "RR Soares",
          "url": "https://www.bestrongest.com.br/podcasts/cursofe/files/cursofe05.mp3",
          "artwork": "https://www.bestrongest.com.br/podcasts/cursofe/cursofe-album-cover.png"
        },
        {
          "id": "6",
          "title": "A derrota de satanás",
          "artist": "RR Soares",
          "url": "https://www.bestrongest.com.br/podcasts/cursofe/files/cursofe06.mp3",
          "artwork": "https://www.bestrongest.com.br/podcasts/cursofe/cursofe-album-cover.png"
        },
        {
          "id": "7",
          "title": "Resistir",
          "artist": "RR Soares",
          "url": "https://www.bestrongest.com.br/podcasts/cursofe/files/cursofe07.mp3",
          "artwork": "https://www.bestrongest.com.br/podcasts/cursofe/cursofe-album-cover.png"
        },
        {
          "id": "8",
          "title": "Mais que vencedores",
          "artist": "RR Soares",
          "url": "https://www.bestrongest.com.br/podcasts/cursofe/files/cursofe08.mp3",
          "artwork": "https://www.bestrongest.com.br/podcasts/cursofe/cursofe-album-cover.png"
        },
        {
          "id": "9",
          "title": "As palavras",
          "artist": "RR Soares",
          "url": "https://www.bestrongest.com.br/podcasts/cursofe/files/cursofe09.mp3",
          "artwork": "https://www.bestrongest.com.br/podcasts/cursofe/cursofe-album-cover.png"
        },
        {
          "id": "10",
          "title": "Confissão",
          "artist": "RR Soares",
          "url": "https://www.bestrongest.com.br/podcasts/cursofe/files/cursofe10.mp3",
          "artwork": "https://www.bestrongest.com.br/podcasts/cursofe/cursofe-album-cover.png"
        },
        {
          "id": "11",
          "title": "Vãs repetições",
          "artist": "RR Soares",
          "url": "https://www.bestrongest.com.br/podcasts/cursofe/files/cursofe11.mp3",
          "artwork": "https://www.bestrongest.com.br/podcasts/cursofe/cursofe-album-cover.png"
        },
        {
          "id": "12",
          "title": "Realizando a obra de Deus",
          "artist": "RR Soares",
          "url": "https://www.bestrongest.com.br/podcasts/cursofe/files/cursofe12.mp3",
          "artwork": "https://www.bestrongest.com.br/podcasts/cursofe/cursofe-album-cover.png"
        }
      ]
    },
    {
      "id": 3,
      "title": "Ministrações",
      "artist": "Jaime de Amorim",
      "cover": "https://www.bestrongest.com.br/podcasts/iigd/iigd-album-cover.png",
      "tracks": [
        {
          "id": "16",
          "title": "Entregue teu coração ao Senhor",
          "artist": "Jaime de Amorim",
          "url": "https://www.bestrongest.com.br/podcasts/iigd/files/MSG08112015.2000.mp3",
          "artwork": "https://www.bestrongest.com.br/podcasts/iigd/iigd-album-cover.png"
        },
        {
          "id": "15",
          "title": "Seja dependente do Senhor",
          "artist": "Jaime de Amorim",
          "url": "https://www.bestrongest.com.br/podcasts/iigd/files/MSG15102017.1630.mp3",
          "artwork": "https://www.bestrongest.com.br/podcasts/iigd/iigd-album-cover.png"
        },
        {
          "id": "14",
          "title": "Prepare o seu coração",
          "artist": "Jaime de Amorim",
          "url": "https://www.bestrongest.com.br/podcasts/iigd/files/MSG29112015.1800.mp3",
          "artwork": "https://www.bestrongest.com.br/podcasts/iigd/iigd-album-cover.png"
        },        
        {
          "id": "13",
          "title": "Vencendo as tentações",
          "artist": "Jaime de Amorim",
          "url": "https://www.bestrongest.com.br/podcasts/iigd/files/MSG25102015.1600.mp3",
          "artwork": "https://www.bestrongest.com.br/podcasts/iigd/iigd-album-cover.png"
        },
        {
          "id": "12",
          "title": "Busque andar na palavra",
          "artist": "Jaime de Amorim",
          "url": "https://www.bestrongest.com.br/podcasts/iigd/files/MSG10012016.1900.mp3",
          "artwork": "https://www.bestrongest.com.br/podcasts/iigd/iigd-album-cover.png"
        },
        {
          "id": "11",
          "title": "Quem teme Deus não teme o mal",
          "artist": "Jaime de Amorim",
          "url": "https://www.bestrongest.com.br/podcasts/iigd/files/MSG31012016.1500.mp3",
          "artwork": "https://www.bestrongest.com.br/podcasts/iigd/iigd-album-cover.png"
        },
        {
          "id": "10",
          "title": "Peça sempre direção ao Senhor",
          "artist": "Jaime de Amorim",
          "url": "https://www.bestrongest.com.br/podcasts/iigd/files/MSG06032016.1800.mp3",
          "artwork": "https://www.bestrongest.com.br/podcasts/iigd/iigd-album-cover.png"
        },        
        {
          "id": "9",
          "title": "Busque ter confiança no Senhor",
          "artist": "Jaime de Amorim",
          "url": "https://www.bestrongest.com.br/podcasts/iigd/files/MSG13032016.1900.mp3",
          "artwork": "https://www.bestrongest.com.br/podcasts/iigd/iigd-album-cover.png"
        },
        {
          "id": "8",
          "title": "Deixe Deus falar ao seu coração",
          "artist": "Jaime de Amorim",
          "url": "https://www.bestrongest.com.br/podcasts/iigd/files/MSG27032017.1600.mp3",
          "artwork": "https://www.bestrongest.com.br/podcasts/iigd/iigd-album-cover.png"
        },
        {
          "id": "7",
          "title": "Siga a luz",
          "artist": "Jaime de Amorim",
          "url": "https://www.bestrongest.com.br/podcasts/iigd/files/MSG14052017.2000.mp3",
          "artwork": "https://www.bestrongest.com.br/podcasts/iigd/iigd-album-cover.png"
        },
        {
          "id": "6",
          "title": "A Justiça de Deus",
          "artist": "Jaime de Amorim",
          "url": "https://www.bestrongest.com.br/podcasts/iigd/files/MSG22042017.1800.mp3",
          "artwork": "https://www.bestrongest.com.br/podcasts/iigd/iigd-album-cover.png"
        },
        {
          "id": "5",
          "title": "Viva na liberdade de Cristo",
          "artist": "Jaime de Amorim",
          "url": "https://www.bestrongest.com.br/podcasts/iigd/files/MSG08112015.1600.mp3",
          "artwork": "https://www.bestrongest.com.br/podcasts/iigd/iigd-album-cover.png"
        },
        {
          "id": "4",
          "title": "Permita Deus entrar na sua vida",
          "artist": "Jaime de Amorim",
          "url": "https://www.bestrongest.com.br/podcasts/iigd/files/MSG22102017.1800.mp3",
          "artwork": "https://www.bestrongest.com.br/podcasts/iigd/iigd-album-cover.png"
        },
                {
          "id": "3",
          "title": "A importancia de Temer a Deus",
          "artist": "Jaime de Amorim",
          "url": "https://www.bestrongest.com.br/podcasts/iigd/files/MSG26032017.1900.mp3",
          "artwork": "https://www.bestrongest.com.br/podcasts/iigd/iigd-album-cover.png"
        },
                {
          "id": "2",
          "title": "Para Deus nada é impossível",
          "artist": "Jaime de Amorim",
          "url": "https://www.bestrongest.com.br/podcasts/iigd/files/MSG21072019.1400.mp3",
          "artwork": "https://www.bestrongest.com.br/podcasts/iigd/iigd-album-cover.png"
        },
                {
          "id": "1",
          "title": "Busque o melhor de Deus",
          "artist": "Jaime de Amorim",
          "url": "https://www.bestrongest.com.br/podcasts/iigd/files/MSG19112017.1900.mp3",
          "artwork": "https://www.bestrongest.com.br/podcasts/iigd/iigd-album-cover.png"
        }
      ]
    },
    {
      "id": 4,
      "title": "Adoração",
      "artist": "Culto Ao Vivo",
      "cover": "https://www.bestrongest.com.br/podcasts/worship/worship-album-cover.png",
      "tracks": [
        {
          "id": "20",
          "title": "Faça Morada",
          "artist": "Culto Ao Vivo",
          "url": "https://www.bestrongest.com.br/podcasts/worship/files/faca_morada.mp3",
          "artwork": "https://www.bestrongest.com.br/podcasts/worship/worship-album-cover.png"
        },
        {
          "id": "19",
          "title": "A Casa É Sua",
          "artist": "Culto Ao Vivo",
          "url": "https://www.bestrongest.com.br/podcasts/worship/files/a_casa_e_sua.mp3",
          "artwork": "https://www.bestrongest.com.br/podcasts/worship/worship-album-cover.png"
        },
        {
          "id": "18",
          "title": "Há um lugar",
          "artist": "Culto Ao Vivo",
          "url": "https://www.bestrongest.com.br/podcasts/worship/files/ha_um_lugar.mp3",
          "artwork": "https://www.bestrongest.com.br/podcasts/worship/worship-album-cover.png"
        },
        {
          "id": "17",
          "title": "Que Ele Cresça",
          "artist": "Culto Ao Vivo",
          "url": "https://www.bestrongest.com.br/podcasts/worship/files/que_ele_cresca.mp3",
          "artwork": "https://www.bestrongest.com.br/podcasts/worship/worship-album-cover.png"
        },
        {
          "id": "16",
          "title": "Nada Além do Sangue",
          "artist": "Culto Ao Vivo",
          "url": "https://www.bestrongest.com.br/podcasts/worship/files/nada_alem_do_sangue.mp3",
          "artwork": "https://www.bestrongest.com.br/podcasts/worship/worship-album-cover.png"
        },
        {
          "id": "15",
          "title": "Primeiro Amor",
          "artist": "Culto Ao Vivo",
          "url": "https://www.bestrongest.com.br/podcasts/worship/files/primeiro_amor.mp3",
          "artwork": "https://www.bestrongest.com.br/podcasts/worship/worship-album-cover.png"
        },
        {
          "id": "14",
          "title": "Eu Navegarei",
          "artist": "Culto Ao Vivo",
          "url": "https://www.bestrongest.com.br/podcasts/worship/files/eu_navegarei.mp3",
          "artwork": "https://www.bestrongest.com.br/podcasts/worship/worship-album-cover.png"
        },        
        {
          "id": "13",
          "title": "Sonda-me, Usa-me",
          "artist": "Culto Ao Vivo",
          "url": "https://www.bestrongest.com.br/podcasts/worship/files/sonda-me_usa-me.mp3",
          "artwork": "https://www.bestrongest.com.br/podcasts/worship/worship-album-cover.png"
        },
        {
          "id": "12",
          "title": "Vem Agora Espírito Santo",
          "artist": "Culto Ao Vivo",
          "url": "https://www.bestrongest.com.br/podcasts/worship/files/vem_agora_espirito_santo.mp3",
          "artwork": "https://www.bestrongest.com.br/podcasts/worship/worship-album-cover.png"
        },
        {
          "id": "11",
          "title": "Atrai o Meu Coração",
          "artist": "Culto Ao Vivo",
          "url": "https://www.bestrongest.com.br/podcasts/worship/files/atrai_o_meu_coracao.mp3",
          "artwork": "https://www.bestrongest.com.br/podcasts/worship/worship-album-cover.png"
        },
        {
          "id": "10",
          "title": "A Jesus seguirei",
          "artist": "Culto Ao Vivo",
          "url": "https://www.bestrongest.com.br/podcasts/worship/files/a_jesus_seguirei.mp3",
          "artwork": "https://www.bestrongest.com.br/podcasts/worship/worship-album-cover.png"
        },
        {
          "id": "9",
          "title": "Deus Pode Tudo",
          "artist": "Culto Ao Vivo",
          "url": "https://www.bestrongest.com.br/podcasts/worship/files/deus_pode_tudo.mp3",
          "artwork": "https://www.bestrongest.com.br/podcasts/worship/worship-album-cover.png"
        },
        {
          "id": "8",
          "title": "Mostra-me Tua Glória",
          "artist": "Culto Ao Vivo",
          "url": "https://www.bestrongest.com.br/podcasts/worship/files/mostra-me_tua_gloria.mp3",
          "artwork": "https://www.bestrongest.com.br/podcasts/worship/worship-album-cover.png"
        },
        {
          "id": "7",
          "title": "Consagração",
          "artist": "Culto Ao Vivo",
          "url": "https://www.bestrongest.com.br/podcasts/worship/files/consagracao.mp3",
          "artwork": "https://www.bestrongest.com.br/podcasts/worship/worship-album-cover.png"
        },
        {
          "id": "6",
          "title": "Se Eu Me Humilhar",
          "artist": "Culto Ao Vivo",
          "url": "https://www.bestrongest.com.br/podcasts/worship/files/se_eu_me_humilhar.mp3",
          "artwork": "https://www.bestrongest.com.br/podcasts/worship/worship-album-cover.png"
        },
        {
          "id": "5",
          "title": "Junto a Ti",
          "artist": "Culto Ao Vivo",
          "url": "https://www.bestrongest.com.br/podcasts/worship/files/junto_a_ti.mp3",
          "artwork": "https://www.bestrongest.com.br/podcasts/worship/worship-album-cover.png"
        },
        {
          "id": "4",
          "title": "Em Tua Presença",
          "artist": "Culto Ao Vivo",
          "url": "https://www.bestrongest.com.br/podcasts/worship/files/em_tua_presenca.mp3",
          "artwork": "https://www.bestrongest.com.br/podcasts/worship/worship-album-cover.png"
        },
        {
          "id": "3",
          "title": "Deixa-me Tocar",
          "artist": "Culto Ao Vivo",
          "url": "https://www.bestrongest.com.br/podcasts/worship/files/deixa-me_tocar.mp3",
          "artwork": "https://www.bestrongest.com.br/podcasts/worship/worship-album-cover.png"
        },
        {
          "id": "2",
          "title": "Renova-me",
          "artist": "Culto Ao Vivo",
          "url": "https://www.bestrongest.com.br/podcasts/worship/files/renova-me.mp3",
          "artwork": "https://www.bestrongest.com.br/podcasts/worship/worship-album-cover.png"
        },
        {
          "id": "1",
          "title": "Venha o Teu Reino",
          "artist": "Culto Ao Vivo",
          "url": "https://www.bestrongest.com.br/podcasts/worship/files/venha_o_teu_reino.mp3",
          "artwork": "https://www.bestrongest.com.br/podcasts/worship/worship-album-cover.png"
        }
      ]
    }
  ]
}

